vis3/alembic_vis3/README
vis3/alembic_vis3/alembic.ini
vis3/alembic_vis3/env.py
vis3/alembic_vis3/run_migrate.py
vis3/alembic_vis3/script.py.mako
vis3/alembic_vis3/versions/36abca001cd5_remove_name_in_bucket.py
vis3/internal/__init__.py
vis3/internal/api/__init__.py
vis3/internal/api/dependencies/__init__.py
vis3/internal/api/dependencies/auth.py
vis3/internal/api/v1/__init__.py
vis3/internal/api/v1/endpoints/__init__.py
vis3/internal/api/v1/endpoints/auth.py
vis3/internal/api/v1/endpoints/bucket.py
vis3/internal/api/v1/endpoints/keychain.py
vis3/internal/api/v1/schema/request/bucket.py
vis3/internal/api/v1/schema/request/keychain.py
vis3/internal/api/v1/schema/request/user.py
vis3/internal/api/v1/schema/response/__init__.py
vis3/internal/api/v1/schema/response/bucket.py
vis3/internal/api/v1/schema/response/keychain.py
vis3/internal/api/v1/schema/response/user.py
vis3/internal/client/s3_reader.py
vis3/internal/common/db.py
vis3/internal/common/exceptions.py
vis3/internal/common/io.py
vis3/internal/config.py
vis3/internal/crud/__init__.py
vis3/internal/crud/base.py
vis3/internal/crud/bucket.py
vis3/internal/crud/keychain.py
vis3/internal/crud/user.py
vis3/internal/middleware/__init__.py
vis3/internal/middleware/content_type.py
vis3/internal/middleware/tracing.py
vis3/internal/models/__init__.py
vis3/internal/models/bucket.py
vis3/internal/models/keychain.py
vis3/internal/models/user.py
vis3/internal/schema/__init__.py
vis3/internal/schema/keychain.py
vis3/internal/schema/state.py
vis3/internal/schema/user.py
vis3/internal/service/bucket.py
vis3/internal/statics/__init__.py
vis3/internal/statics/aliyun.png
vis3/internal/statics/assets/LockOutlined-Jqd_iPHc.js
vis3/internal/statics/assets/index-6rLuIUKq.js
vis3/internal/statics/assets/index-B7kPkC0D.js
vis3/internal/statics/assets/index-BcRp0SKY.css
vis3/internal/statics/assets/index-C-ku7Uvl.js
vis3/internal/statics/assets/index-CHtTHo2p.css
vis3/internal/statics/assets/index-Ck1VEtkP.css
vis3-1.3.0.dist-info/LICENSE
vis3-1.3.0.dist-info/METADATA
vis3-1.3.0.dist-info/WHEEL
vis3-1.3.0.dist-info/entry_points.txt
vis3-1.3.0.dist-info/RECORD
